setup.py
free4my/__init__.py
free4my/db.py
free4my/dynamic.py
free4my/session.py
free4my/utils.py
free4my.egg-info/PKG-INFO
free4my.egg-info/SOURCES.txt
free4my.egg-info/dependency_links.txt
free4my.egg-info/top_level.txt