Metadata-Version: 1.0
Name: free4my
Version: 0.10
Summary: a easy to use schema free DAL for mysql
Home-page: https://github.com/ipconfiger/free4my
Author: Alexander.Li
Author-email: superpowerlee@gmail.com
License: Apache License 2.0
Platform: UNKNOWN
